{
  "2017-01-17_10:00:00-14:00:00": {
    "date": "2017-01-17",
    "interval": [
      "10:00:00",
      "14:00:00"
    ],
    "H0": "multiexp_fixed_betas",
    "method": "naive",
    "alpha_level": 0.05,
    "KS": false,
    "CvM": false,
    "AD": false,
    "estimated_params": {
      "mu": 0.09184965832922831,
      "alphas": [
        74.64937337225817,
        474.3502855170528,
        0.03923846797143688
      ],
      "betas": [
        216459.0,
        766.0,
        0.24
      ],
      "T": 14400.0,
      "J": 3
    },
    "branching_ratios": [
      0.0003448661103130762,
      0.619256247411296,
      0.16349361654765368
    ],
    "time_seconds": 3.7482255999984773
  },
  "2017-01-17_11:00:00-15:00:00": {
    "date": "2017-01-17",
    "interval": [
      "11:00:00",
      "15:00:00"
    ],
    "H0": "multiexp_fixed_betas",
    "method": "naive",
    "alpha_level": 0.05,
    "KS": false,
    "CvM": false,
    "AD": false,
    "estimated_params": {
      "mu": 0.09954979135545133,
      "alphas": [
        74.49112260310008,
        477.2036892577046,
        0.03863520246157925
      ],
      "betas": [
        216459.0,
        766.0,
        0.24
      ],
      "T": 14400.0,
      "J": 3
    },
    "branching_ratios": [
      0.0003441350214271529,
      0.6229813175688049,
      0.1609800102565802
    ],
    "time_seconds": 2.4301550000000134
  },
  "2017-01-17_12:00:00-16:00:00": {
    "date": "2017-01-17",
    "interval": [
      "12:00:00",
      "16:00:00"
    ],
    "H0": "multiexp_fixed_betas",
    "method": "naive",
    "alpha_level": 0.05,
    "KS": false,
    "CvM": false,
    "AD": false,
    "estimated_params": {
      "mu": 0.10738598051818644,
      "alphas": [
        72.09229589469692,
        466.79871617382264,
        0.041579143461655955
      ],
      "betas": [
        216459.0,
        766.0,
        0.24
      ],
      "T": 14400.0,
      "J": 3
    },
    "branching_ratios": [
      0.00033305289174715265,
      0.6093978017935021,
      0.17324643109023316
    ],
    "time_seconds": 2.451509000000442
  },
  "2017-01-18_10:00:00-14:00:00": {
    "date": "2017-01-18",
    "interval": [
      "10:00:00",
      "14:00:00"
    ],
    "H0": "multiexp_fixed_betas",
    "method": "naive",
    "alpha_level": 0.05,
    "KS": false,
    "CvM": false,
    "AD": false,
    "estimated_params": {
      "mu": 0.07112211977741885,
      "alphas": [
        66.72410959065073,
        460.47490332566997,
        0.032053620023999314
      ],
      "betas": [
        216459.0,
        766.0,
        0.24
      ],
      "T": 14400.0,
      "J": 3
    },
    "branching_ratios": [
      0.0003082528774070412,
      0.6011421714434334,
      0.13355675009999715
    ],
    "time_seconds": 1.6006266000003961
  },
  "2017-01-18_11:00:00-15:00:00": {
    "date": "2017-01-18",
    "interval": [
      "11:00:00",
      "15:00:00"
    ],
    "H0": "multiexp_fixed_betas",
    "method": "naive",
    "alpha_level": 0.05,
    "KS": false,
    "CvM": false,
    "AD": false,
    "estimated_params": {
      "mu": 0.0705392498765313,
      "alphas": [
        68.14913007742298,
        473.33299236172746,
        0.03053512773131879
      ],
      "betas": [
        216459.0,
        766.0,
        0.24
      ],
      "T": 14400.0,
      "J": 3
    },
    "branching_ratios": [
      0.00031483620490449916,
      0.6179281884617852,
      0.12722969888049496
    ],
    "time_seconds": 1.579169799999363
  },
  "2017-01-18_12:00:00-16:00:00": {
    "date": "2017-01-18",
    "interval": [
      "12:00:00",
      "16:00:00"
    ],
    "H0": "multiexp_fixed_betas",
    "method": "naive",
    "alpha_level": 0.05,
    "KS": false,
    "CvM": false,
    "AD": true,
    "estimated_params": {
      "mu": 0.06879158342874586,
      "alphas": [
        68.35321337593712,
        493.50211631635807,
        0.03316714427292093
      ],
      "betas": [
        216459.0,
        766.0,
        0.24
      ],
      "T": 14400.0,
      "J": 3
    },
    "branching_ratios": [
      0.0003157790314837319,
      0.6442586374887181,
      0.1381964344705039
    ],
    "time_seconds": 1.5478070000008302
  },
  "2017-01-19_10:00:00-14:00:00": {
    "date": "2017-01-19",
    "interval": [
      "10:00:00",
      "14:00:00"
    ],
    "H0": "multiexp_fixed_betas",
    "method": "naive",
    "alpha_level": 0.05,
    "KS": false,
    "CvM": false,
    "AD": false,
    "estimated_params": {
      "mu": 0.06997871504380192,
      "alphas": [
        71.25372868786854,
        466.9933818875719,
        0.04207432816481005
      ],
      "betas": [
        216459.0,
        766.0,
        0.24
      ],
      "T": 14400.0,
      "J": 3
    },
    "branching_ratios": [
      0.0003291788684594706,
      0.6096519345790756,
      0.17530970068670854
    ],
    "time_seconds": 1.9880819999998494
  },
  "2017-01-19_11:00:00-15:00:00": {
    "date": "2017-01-19",
    "interval": [
      "11:00:00",
      "15:00:00"
    ],
    "H0": "multiexp_fixed_betas",
    "method": "naive",
    "alpha_level": 0.05,
    "KS": false,
    "CvM": false,
    "AD": true,
    "estimated_params": {
      "mu": 0.06734951966888772,
      "alphas": [
        72.25059531628875,
        480.56398997715604,
        0.046551173340169415
      ],
      "betas": [
        216459.0,
        766.0,
        0.24
      ],
      "T": 14400.0,
      "J": 3
    },
    "branching_ratios": [
      0.000333784205398199,
      0.6273681331294465,
      0.1939632222507059
    ],
    "time_seconds": 1.9682336999994732
  },
  "2017-01-19_12:00:00-16:00:00": {
    "date": "2017-01-19",
    "interval": [
      "12:00:00",
      "16:00:00"
    ],
    "H0": "multiexp_fixed_betas",
    "method": "naive",
    "alpha_level": 0.05,
    "KS": false,
    "CvM": false,
    "AD": true,
    "estimated_params": {
      "mu": 0.0758278581023424,
      "alphas": [
        70.12509835187134,
        482.06201273960755,
        0.04937125383981892
      ],
      "betas": [
        216459.0,
        766.0,
        0.24
      ],
      "T": 14400.0,
      "J": 3
    },
    "branching_ratios": [
      0.00032396480789374126,
      0.6293237764224642,
      0.20571355766591218
    ],
    "time_seconds": 2.0248819999997067
  },
  "2017-01-20_10:00:00-14:00:00": {
    "date": "2017-01-20",
    "interval": [
      "10:00:00",
      "14:00:00"
    ],
    "H0": "multiexp_fixed_betas",
    "method": "naive",
    "alpha_level": 0.05,
    "KS": true,
    "CvM": true,
    "AD": true,
    "estimated_params": {
      "mu": 0.07963495375535694,
      "alphas": [
        85.24882705005881,
        503.3523005125192,
        0.05433699588298141
      ],
      "betas": [
        216459.0,
        766.0,
        0.24
      ],
      "T": 14400.0,
      "J": 3
    },
    "branching_ratios": [
      0.000393833599203816,
      0.6571178857865786,
      0.22640414951242255
    ],
    "time_seconds": 2.2215464999990218
  },
  "2017-01-20_11:00:00-15:00:00": {
    "date": "2017-01-20",
    "interval": [
      "11:00:00",
      "15:00:00"
    ],
    "H0": "multiexp_fixed_betas",
    "method": "naive",
    "alpha_level": 0.05,
    "KS": true,
    "CvM": true,
    "AD": true,
    "estimated_params": {
      "mu": 0.06384143587889556,
      "alphas": [
        88.314992151886,
        510.82284741924985,
        0.05422128396720199
      ],
      "betas": [
        216459.0,
        766.0,
        0.24
      ],
      "T": 14400.0,
      "J": 3
    },
    "branching_ratios": [
      0.00040799870715417703,
      0.6668705579885769,
      0.2259220165300083
    ],
    "time_seconds": 2.1473759000000427
  },
  "2017-01-20_12:00:00-16:00:00": {
    "date": "2017-01-20",
    "interval": [
      "12:00:00",
      "16:00:00"
    ],
    "H0": "multiexp_fixed_betas",
    "method": "naive",
    "alpha_level": 0.05,
    "KS": true,
    "CvM": true,
    "AD": true,
    "estimated_params": {
      "mu": 0.07007332067638303,
      "alphas": [
        79.76662406463265,
        462.19325496488335,
        0.05410909400050091
      ],
      "betas": [
        216459.0,
        766.0,
        0.24
      ],
      "T": 14400.0,
      "J": 3
    },
    "branching_ratios": [
      0.0003685068491706635,
      0.6033854503458007,
      0.22545455833542047
    ],
    "time_seconds": 2.0493995000015275
  },
  "2017-01-23_10:00:00-14:00:00": {
    "date": "2017-01-23",
    "interval": [
      "10:00:00",
      "14:00:00"
    ],
    "H0": "multiexp_fixed_betas",
    "method": "naive",
    "alpha_level": 0.05,
    "KS": false,
    "CvM": false,
    "AD": false,
    "estimated_params": {
      "mu": 0.08498143554206719,
      "alphas": [
        82.5984047959398,
        475.44037829237647,
        0.0350354338993744
      ],
      "betas": [
        216459.0,
        766.0,
        0.24
      ],
      "T": 14400.0,
      "J": 3
    },
    "branching_ratios": [
      0.00038158914526972685,
      0.6206793450292121,
      0.14598097458072667
    ],
    "time_seconds": 1.657926600000792
  },
  "2017-01-23_11:00:00-15:00:00": {
    "date": "2017-01-23",
    "interval": [
      "11:00:00",
      "15:00:00"
    ],
    "H0": "multiexp_fixed_betas",
    "method": "naive",
    "alpha_level": 0.05,
    "KS": false,
    "CvM": false,
    "AD": false,
    "estimated_params": {
      "mu": 0.08331089508223428,
      "alphas": [
        81.44037929911038,
        480.7648016345584,
        0.025519736524916563
      ],
      "betas": [
        216459.0,
        766.0,
        0.24
      ],
      "T": 14400.0,
      "J": 3
    },
    "branching_ratios": [
      0.00037623928457172204,
      0.6276302893401546,
      0.10633223552048568
    ],
    "time_seconds": 1.6963197999994009
  },
  "2017-01-23_12:00:00-16:00:00": {
    "date": "2017-01-23",
    "interval": [
      "12:00:00",
      "16:00:00"
    ],
    "H0": "multiexp_fixed_betas",
    "method": "naive",
    "alpha_level": 0.05,
    "KS": false,
    "CvM": false,
    "AD": false,
    "estimated_params": {
      "mu": 0.08921322225172608,
      "alphas": [
        79.5612219145216,
        480.6395257758011,
        0.024315017300364058
      ],
      "betas": [
        216459.0,
        766.0,
        0.24
      ],
      "T": 14400.0,
      "J": 3
    },
    "branching_ratios": [
      0.00036755792974430077,
      0.6274667438326385,
      0.10131257208485024
    ],
    "time_seconds": 1.6964795000003505
  },
  "2017-01-24_10:00:00-14:00:00": {
    "date": "2017-01-24",
    "interval": [
      "10:00:00",
      "14:00:00"
    ],
    "H0": "multiexp_fixed_betas",
    "method": "naive",
    "alpha_level": 0.05,
    "KS": false,
    "CvM": false,
    "AD": false,
    "estimated_params": {
      "mu": 0.07418392507941167,
      "alphas": [
        77.28877353922039,
        495.5228654050318,
        0.029409437050467627
      ],
      "betas": [
        216459.0,
        766.0,
        0.24
      ],
      "T": 14400.0,
      "J": 3
    },
    "branching_ratios": [
      0.0003570596442708337,
      0.6468966911292843,
      0.12253932104361512
    ],
    "time_seconds": 1.4760619000007864
  },
  "2017-01-24_11:00:00-15:00:00": {
    "date": "2017-01-24",
    "interval": [
      "11:00:00",
      "15:00:00"
    ],
    "H0": "multiexp_fixed_betas",
    "method": "naive",
    "alpha_level": 0.05,
    "KS": false,
    "CvM": false,
    "AD": false,
    "estimated_params": {
      "mu": 0.06422933037055101,
      "alphas": [
        78.5367905326518,
        511.85858519526244,
        0.02194262047026535
      ],
      "betas": [
        216459.0,
        766.0,
        0.24
      ],
      "T": 14400.0,
      "J": 3
    },
    "branching_ratios": [
      0.00036282524881225454,
      0.6682226960773661,
      0.0914275852927723
    ],
    "time_seconds": 1.430452199998399
  },
  "2017-01-24_12:00:00-16:00:00": {
    "date": "2017-01-24",
    "interval": [
      "12:00:00",
      "16:00:00"
    ],
    "H0": "multiexp_fixed_betas",
    "method": "naive",
    "alpha_level": 0.05,
    "KS": false,
    "CvM": false,
    "AD": false,
    "estimated_params": {
      "mu": 0.06358506792892808,
      "alphas": [
        79.55470706697544,
        512.9623994540474,
        0.02458050875430256
      ],
      "betas": [
        216459.0,
        766.0,
        0.24
      ],
      "T": 14400.0,
      "J": 3
    },
    "branching_ratios": [
      0.00036752783236998894,
      0.6696637068590697,
      0.10241878647626067
    ],
    "time_seconds": 1.4458367999995971
  },
  "2017-01-25_10:00:00-14:00:00": {
    "date": "2017-01-25",
    "interval": [
      "10:00:00",
      "14:00:00"
    ],
    "H0": "multiexp_fixed_betas",
    "method": "naive",
    "alpha_level": 0.05,
    "KS": false,
    "CvM": false,
    "AD": false,
    "estimated_params": {
      "mu": 0.08942632841662217,
      "alphas": [
        75.39713126712694,
        495.3362898641943,
        0.03191732287124645
      ],
      "betas": [
        216459.0,
        766.0,
        0.24
      ],
      "T": 14400.0,
      "J": 3
    },
    "branching_ratios": [
      0.00034832061160370756,
      0.6466531199271467,
      0.1329888452968602
    ],
    "time_seconds": 1.6701952000003075
  },
  "2017-01-25_11:00:00-15:00:00": {
    "date": "2017-01-25",
    "interval": [
      "11:00:00",
      "15:00:00"
    ],
    "H0": "multiexp_fixed_betas",
    "method": "naive",
    "alpha_level": 0.05,
    "KS": false,
    "CvM": false,
    "AD": false,
    "estimated_params": {
      "mu": 0.08303464863158841,
      "alphas": [
        74.95364607880613,
        499.0607398140049,
        0.031598540207602464
      ],
      "betas": [
        216459.0,
        766.0,
        0.24
      ],
      "T": 14400.0,
      "J": 3
    },
    "branching_ratios": [
      0.0003462717931747173,
      0.6515153261279437,
      0.13166058419834362
    ],
    "time_seconds": 1.5776571000005788
  },
  "2017-01-25_12:00:00-16:00:00": {
    "date": "2017-01-25",
    "interval": [
      "12:00:00",
      "16:00:00"
    ],
    "H0": "multiexp_fixed_betas",
    "method": "naive",
    "alpha_level": 0.05,
    "KS": false,
    "CvM": false,
    "AD": false,
    "estimated_params": {
      "mu": 0.09147988047458395,
      "alphas": [
        75.01791861646252,
        493.951078576257,
        0.036731535254658866
      ],
      "betas": [
        216459.0,
        766.0,
        0.24
      ],
      "T": 14400.0,
      "J": 3
    },
    "branching_ratios": [
      0.00034656872024938916,
      0.6448447500995522,
      0.1530480635610786
    ],
    "time_seconds": 1.6658103999998275
  },
  "2017-01-26_10:00:00-14:00:00": {
    "date": "2017-01-26",
    "interval": [
      "10:00:00",
      "14:00:00"
    ],
    "H0": "multiexp_fixed_betas",
    "method": "naive",
    "alpha_level": 0.05,
    "KS": false,
    "CvM": true,
    "AD": true,
    "estimated_params": {
      "mu": 0.09787992619073276,
      "alphas": [
        73.83775598934051,
        494.7730656983252,
        0.03212651184373798
      ],
      "betas": [
        216459.0,
        766.0,
        0.24
      ],
      "T": 14400.0,
      "J": 3
    },
    "branching_ratios": [
      0.00034111659015952447,
      0.6459178403372391,
      0.1338604660155749
    ],
    "time_seconds": 1.8867903999998816
  },
  "2017-01-26_11:00:00-15:00:00": {
    "date": "2017-01-26",
    "interval": [
      "11:00:00",
      "15:00:00"
    ],
    "H0": "multiexp_fixed_betas",
    "method": "naive",
    "alpha_level": 0.05,
    "KS": false,
    "CvM": false,
    "AD": false,
    "estimated_params": {
      "mu": 0.08880410985012402,
      "alphas": [
        72.33611953191038,
        491.0777758956702,
        0.03204741998737724
      ],
      "betas": [
        216459.0,
        766.0,
        0.24
      ],
      "T": 14400.0,
      "J": 3
    },
    "branching_ratios": [
      0.0003341793112409758,
      0.6410937022136687,
      0.13353091661407185
    ],
    "time_seconds": 1.885650700000042
  },
  "2017-01-26_12:00:00-16:00:00": {
    "date": "2017-01-26",
    "interval": [
      "12:00:00",
      "16:00:00"
    ],
    "H0": "multiexp_fixed_betas",
    "method": "naive",
    "alpha_level": 0.05,
    "KS": false,
    "CvM": false,
    "AD": false,
    "estimated_params": {
      "mu": 0.09682772355877518,
      "alphas": [
        67.91413825532436,
        486.58703665096465,
        0.03359281572915219
      ],
      "betas": [
        216459.0,
        766.0,
        0.24
      ],
      "T": 14400.0,
      "J": 3
    },
    "branching_ratios": [
      0.0003137505867407886,
      0.6352311183432959,
      0.13997006553813413
    ],
    "time_seconds": 1.8886241000000155
  },
  "2017-01-27_10:00:00-14:00:00": {
    "date": "2017-01-27",
    "interval": [
      "10:00:00",
      "14:00:00"
    ],
    "H0": "multiexp_fixed_betas",
    "method": "naive",
    "alpha_level": 0.05,
    "KS": false,
    "CvM": false,
    "AD": false,
    "estimated_params": {
      "mu": 0.08191682892508277,
      "alphas": [
        72.14798595577768,
        487.24944216889145,
        0.04514396167409021
      ],
      "betas": [
        216459.0,
        766.0,
        0.24
      ],
      "T": 14400.0,
      "J": 3
    },
    "branching_ratios": [
      0.0003333101693890191,
      0.6360958775050802,
      0.18809984030870922
    ],
    "time_seconds": 2.0756154999999126
  },
  "2017-01-27_11:00:00-15:00:00": {
    "date": "2017-01-27",
    "interval": [
      "11:00:00",
      "15:00:00"
    ],
    "H0": "multiexp_fixed_betas",
    "method": "naive",
    "alpha_level": 0.05,
    "KS": false,
    "CvM": false,
    "AD": false,
    "estimated_params": {
      "mu": 0.07208961621019748,
      "alphas": [
        75.45722457680705,
        482.2393528126547,
        0.048754701158077784
      ],
      "betas": [
        216459.0,
        766.0,
        0.24
      ],
      "T": 14400.0,
      "J": 3
    },
    "branching_ratios": [
      0.0003485982314286172,
      0.6295552908781393,
      0.20314458815865744
    ],
    "time_seconds": 1.9656726000011986
  },
  "2017-01-27_12:00:00-16:00:00": {
    "date": "2017-01-27",
    "interval": [
      "12:00:00",
      "16:00:00"
    ],
    "H0": "multiexp_fixed_betas",
    "method": "naive",
    "alpha_level": 0.05,
    "KS": false,
    "CvM": false,
    "AD": false,
    "estimated_params": {
      "mu": 0.07805272817343203,
      "alphas": [
        73.85796147297889,
        467.9726234397765,
        0.04905511251962982
      ],
      "betas": [
        216459.0,
        766.0,
        0.24
      ],
      "T": 14400.0,
      "J": 3
    },
    "branching_ratios": [
      0.0003412099357059715,
      0.6109303178064968,
      0.20439630216512428
    ],
    "time_seconds": 2.0946374000013748
  },
  "2017-01-30_10:00:00-14:00:00": {
    "date": "2017-01-30",
    "interval": [
      "10:00:00",
      "14:00:00"
    ],
    "H0": "multiexp_fixed_betas",
    "method": "naive",
    "alpha_level": 0.05,
    "KS": false,
    "CvM": false,
    "AD": false,
    "estimated_params": {
      "mu": 0.06982220911892947,
      "alphas": [
        71.16682801977258,
        490.4819754146433,
        0.030900131099817534
      ],
      "betas": [
        216459.0,
        766.0,
        0.24
      ],
      "T": 14400.0,
      "J": 3
    },
    "branching_ratios": [
      0.0003287774036643086,
      0.6403158947971844,
      0.12875054624923973
    ],
    "time_seconds": 1.7986110000001645
  },
  "2017-01-30_11:00:00-15:00:00": {
    "date": "2017-01-30",
    "interval": [
      "11:00:00",
      "15:00:00"
    ],
    "H0": "multiexp_fixed_betas",
    "method": "naive",
    "alpha_level": 0.05,
    "KS": false,
    "CvM": false,
    "AD": false,
    "estimated_params": {
      "mu": 0.06264156503701504,
      "alphas": [
        71.10111188523157,
        489.41634979271413,
        0.030771506608567215
      ],
      "betas": [
        216459.0,
        766.0,
        0.24
      ],
      "T": 14400.0,
      "J": 3
    },
    "branching_ratios": [
      0.00032847380744266386,
      0.6389247386327861,
      0.12821461086903008
    ],
    "time_seconds": 1.7773073999996996
  },
  "2017-01-30_12:00:00-16:00:00": {
    "date": "2017-01-30",
    "interval": [
      "12:00:00",
      "16:00:00"
    ],
    "H0": "multiexp_fixed_betas",
    "method": "naive",
    "alpha_level": 0.05,
    "KS": false,
    "CvM": false,
    "AD": true,
    "estimated_params": {
      "mu": 0.06612828327334924,
      "alphas": [
        71.97999149029697,
        506.2951159704761,
        0.03760678808262984
      ],
      "betas": [
        216459.0,
        766.0,
        0.24
      ],
      "T": 14400.0,
      "J": 3
    },
    "branching_ratios": [
      0.00033253406645275535,
      0.6609596814235981,
      0.156694950344291
    ],
    "time_seconds": 1.80298269999912
  },
  "2017-01-31_10:00:00-14:00:00": {
    "date": "2017-01-31",
    "interval": [
      "10:00:00",
      "14:00:00"
    ],
    "H0": "multiexp_fixed_betas",
    "method": "naive",
    "alpha_level": 0.05,
    "KS": false,
    "CvM": false,
    "AD": true,
    "estimated_params": {
      "mu": 0.10600940064129602,
      "alphas": [
        72.26865538782678,
        500.7669896624099,
        0.03361539518018072
      ],
      "betas": [
        216459.0,
        766.0,
        0.24
      ],
      "T": 14400.0,
      "J": 3
    },
    "branching_ratios": [
      0.0003338676395429471,
      0.6537428063477936,
      0.14006414658408634
    ],
    "time_seconds": 2.514203599999746
  },
  "2017-01-31_11:00:00-15:00:00": {
    "date": "2017-01-31",
    "interval": [
      "11:00:00",
      "15:00:00"
    ],
    "H0": "multiexp_fixed_betas",
    "method": "naive",
    "alpha_level": 0.05,
    "KS": false,
    "CvM": false,
    "AD": false,
    "estimated_params": {
      "mu": 0.0977263097701623,
      "alphas": [
        70.45860426349913,
        464.0109191833215,
        0.037748528350228086
      ],
      "betas": [
        216459.0,
        766.0,
        0.24
      ],
      "T": 14400.0,
      "J": 3
    },
    "branching_ratios": [
      0.0003255055426824439,
      0.6057583801348845,
      0.15728553479261703
    ],
    "time_seconds": 2.543610999999146
  },
  "2017-01-31_12:00:00-16:00:00": {
    "date": "2017-01-31",
    "interval": [
      "12:00:00",
      "16:00:00"
    ],
    "H0": "multiexp_fixed_betas",
    "method": "naive",
    "alpha_level": 0.05,
    "KS": false,
    "CvM": false,
    "AD": false,
    "estimated_params": {
      "mu": 0.09654575605788027,
      "alphas": [
        69.61002309810904,
        464.876775850997,
        0.04085310348143261
      ],
      "betas": [
        216459.0,
        766.0,
        0.24
      ],
      "T": 14400.0,
      "J": 3
    },
    "branching_ratios": [
      0.0003215852567835435,
      0.6068887413198394,
      0.17022126450596922
    ],
    "time_seconds": 2.3007974000011018
  },
  "2017-02-01_10:00:00-14:00:00": {
    "date": "2017-02-01",
    "interval": [
      "10:00:00",
      "14:00:00"
    ],
    "H0": "multiexp_fixed_betas",
    "method": "naive",
    "alpha_level": 0.05,
    "KS": true,
    "CvM": false,
    "AD": true,
    "estimated_params": {
      "mu": 0.08000126426283385,
      "alphas": [
        70.63661236994497,
        456.1205001018857,
        0.03577452734577101
      ],
      "betas": [
        216459.0,
        766.0,
        0.24
      ],
      "T": 14400.0,
      "J": 3
    },
    "branching_ratios": [
      0.00032632790676268936,
      0.5954575719345766,
      0.1490605306073792
    ],
    "time_seconds": 1.9346217999991495
  },
  "2017-02-01_11:00:00-15:00:00": {
    "date": "2017-02-01",
    "interval": [
      "11:00:00",
      "15:00:00"
    ],
    "H0": "multiexp_fixed_betas",
    "method": "naive",
    "alpha_level": 0.05,
    "KS": true,
    "CvM": true,
    "AD": true,
    "estimated_params": {
      "mu": 0.07238108784117643,
      "alphas": [
        77.24656547408985,
        476.50728261864793,
        0.03614647738551368
      ],
      "betas": [
        216459.0,
        766.0,
        0.24
      ],
      "T": 14400.0,
      "J": 3
    },
    "branching_ratios": [
      0.00035686465092276066,
      0.6220721705204281,
      0.15061032243964034
    ],
    "time_seconds": 1.9692348999997193
  },
  "2017-02-01_12:00:00-16:00:00": {
    "date": "2017-02-01",
    "interval": [
      "12:00:00",
      "16:00:00"
    ],
    "H0": "multiexp_fixed_betas",
    "method": "naive",
    "alpha_level": 0.05,
    "KS": true,
    "CvM": true,
    "AD": true,
    "estimated_params": {
      "mu": 0.07926067989629348,
      "alphas": [
        75.96301366305207,
        507.57250145924223,
        0.03419998579181492
      ],
      "betas": [
        216459.0,
        766.0,
        0.24
      ],
      "T": 14400.0,
      "J": 3
    },
    "branching_ratios": [
      0.00035093488218578147,
      0.6626272865003162,
      0.14249994079922884
    ],
    "time_seconds": 1.9498823000012635
  }
}